[
   {
      "tugas" : "bahasa Jawa",
      "star" : "1",
      "public" : "Ernesto Yoofi",
      "tags" : "construction", 
      "date" : "Rab, 16 Feb 2022",
      "form" : "@ranilianti.guru",
      "isi_tugas" : "Untuk tugas hari ini silahkan pelajari materi bab Tembang Dolanan. Selanjutnya kerjakan soal uji kompetensi 6 di buku paket Kartika Basa kaca 97-102. Soal pilihan ganda no 1-20. Dikerjakan di buku tulis tidak dikumpulkan."
   },
   {
      "tugas" : "IPA",
      "star" : "1",
      "public" : "Spesana Bot",
      "tags" : "verified", 
      "date" : "Sel, 15 Feb 2022",
      "form" : "@ernesto.tugas",
      "isi_tugas" : "Kerjakan Aktivitas 2 Dan 3 Yang Ada DiLKS, Tidak Difoto Tapi, Dicocokan Minggu Depan"
   },
   {
      "tugas" : "Bahasa Inggris",
      "star" : "1",
      "public" : "Spesana Bot",
      "tags":"verified",
      "date" : "Sel, 15 Feb 2022",
      "form" : "@ernesto.tugas",
      "isi_tugas" : "Artikan Kata Dari Halaman 168-169"
   }
]